{"filename":"2018-01-11-v1.0.0-alpha.19.md","date":"2018-01-11","title":"v1.0.0-alpha.19","tag_name":"v1.0.0-alpha.19","link":"https://github.com/phenomic/phenomic/releases/tag/v1.0.0-alpha.19","author":"MoOx","prerelease":true,"body":{"t":"div","c":[{"t":"h1","p":{"id":"-includes-breaking-changes-for-reason-users"},"c":[{"t":"a","p":{"aria-hidden":true,"href":"#-includes-breaking-changes-for-reason-users"},"c":[{"t":"span","p":{"className":"icon icon-link"}}]},"💥 Includes ",{"t":"em","c":["Breaking changes"]}," for Reason users."]},"\n",{"t":"p","c":["This release is mostly a bunch of improvements (with a minor breaking change)\nfor Reason users in addition to a bugfix for an edge case."]},"\n",{"t":"h2","p":{"id":"-breaking-changes-reason-only"},"c":[{"t":"a","p":{"aria-hidden":true,"href":"#-breaking-changes-reason-only"},"c":[{"t":"span","p":{"className":"icon icon-link"}}]},"💥 Breaking changes (Reason only)"]},"\n",{"t":"ul","c":["\n",{"t":"li","c":[{"t":"a","p":{"href":"https://github.com/phenomic/phenomic/commit/6599f41d4139c430801b44a2e043b60f29a1f4bd"},"c":[{"t":"code","c":["@phenomic/plugin-renderer-react"]},": (Reason) ",{"t":"code","c":["jsEdgeToReason"]}," is now ",{"t":"code","c":["jsEdge"]}]},",\nby @MoOx There is no transformation anymore. Transformation should be made in\nyour component. This change is accompanied with a new type to help you (see\n",{"t":"code","c":["jsNodeList"]}," type below). We highly recommend you to take a look to the\nupdated example. See below for more details."]},"\n"]},"\n",{"t":"h2","p":{"id":"-bugfixes"},"c":[{"t":"a","p":{"aria-hidden":true,"href":"#-bugfixes"},"c":[{"t":"span","p":{"className":"icon icon-link"}}]},"🐛 Bugfixes"]},"\n",{"t":"ul","c":["\n",{"t":"li","c":[{"t":"a","p":{"href":"https://github.com/phenomic/phenomic/commit/a32c7dbd095ba16c703e71d30a935f5d509db81f"},"c":[{"t":"code","c":["@phenomic/core"]},": support query without path for prerendering as it’s supported by database"]},",\nby @MoOx"]},"\n"]},"\n",{"t":"h2","p":{"id":"️-deprecation"},"c":[{"t":"a","p":{"aria-hidden":true,"href":"#️-deprecation"},"c":[{"t":"span","p":{"className":"icon icon-link"}}]},"⚠️ Deprecation"]},"\n",{"t":"ul","c":["\n",{"t":"li","c":[{"t":"a","p":{"href":"https://github.com/phenomic/phenomic/commit/69361b82c856f30727ec5588b098f31831be5637"},"c":[{"t":"code","c":["hasPreviousPage"]}," & ",{"t":"code","c":["hasNextPage"]}," are deprecated"]},",\nby @MoOx Please test directly the existence of ",{"t":"code","c":["previous"]}," and ",{"t":"code","c":["next"]},". It will\ncontinue to work for a while, but will be remove some day. ",{"t":"em","c":["This is to make it\nmore straight forward to use pagination in Reason."]}]},"\n"]},"\n",{"t":"h2","p":{"id":"-improvements"},"c":[{"t":"a","p":{"aria-hidden":true,"href":"#-improvements"},"c":[{"t":"span","p":{"className":"icon icon-link"}}]},"💪 Improvements"]},"\n",{"t":"ul","c":["\n",{"t":"li","c":["\n",{"t":"p","c":[{"t":"a","p":{"href":"https://github.com/phenomic/phenomic/commit/e12b53d464c005e8bf44d66a58099f886870aff8"},"c":[{"t":"code","c":["@phenomic/core"]},": ",{"t":"code","c":["previousPageIsFirst"]}," now always return a value (",{"t":"code","c":["false"]}," instead of ",{"t":"code","c":["undefined"]},")"]},",\nby @MoOx ",{"t":"em","c":["This is to make it more straight forward to use pagination in\nReason."]}]},"\n"]},"\n",{"t":"li","c":["\n",{"t":"p","c":[{"t":"a","p":{"href":"https://github.com/phenomic/phenomic/commit/3d0f24c7e96857d614d3ae1478ce59626f2ea65a"},"c":[{"t":"code","c":["@phenomic/plugin-renderer-react"]},": (Reason) expose ",{"t":"code","c":["jsNodeList"]}," type"]},",\nby @MoOx It is the type of data that comes from list queries."]},"\n"]},"\n"]},"\n",{"t":"h2","p":{"id":"-improved-example-reason"},"c":[{"t":"a","p":{"aria-hidden":true,"href":"#-improved-example-reason"},"c":[{"t":"span","p":{"className":"icon icon-link"}}]},"👌 Improved Example (Reason)"]},"\n",{"t":"p","c":["@MoOx worked a lot on the ",{"t":"code","c":["examples/reason-react-app"]},":"]},"\n",{"t":"ul","c":["\n",{"t":"li","c":["upgrade to reason-react 0.3.1"]},"\n",{"t":"li","c":["we switched to es6 for bs generated files"]},"\n",{"t":"li","c":["we added pagination, like in the JavaScript example"]},"\n",{"t":"li","c":["we added react-helmet usage (via bs-react-helmet)"]},"\n",{"t":"li","c":["we reorganized the code and added tiny helpers"]},"\n"]},"\n",{"t":"hr"},"\n",{"t":"p","c":["♥️ If you have questions, recommendations or improvements to submit, you can\nreach us on our ",{"t":"a","p":{"href":"https://gitter.im/phenomic/phenomic"},"c":["chat"]}," or via the\n",{"t":"a","p":{"href":"https://github.com/phenomic/phenomic/issues/new"},"c":["issues"]}]}]}}